gql/cli.py
gql/clients/__init__.py
gql/clients/asyncio.py
gql/clients/sync.py
gql/config.py
gql/query_parser.py
gql/renderer_dataclasses.py
gql/utils_codegen.py
gql/utils_schema.py
gql_next-0.1.1.dist-info/entry_points.txt
gql_next-0.1.1.dist-info/WHEEL
gql_next-0.1.1.dist-info/METADATA
gql_next-0.1.1.dist-info/RECORD
